commando/__init__.py
commando/commando.py
commando/util.py
pycommando-2.1.3.dist-info/LICENSE
pycommando-2.1.3.dist-info/WHEEL
pycommando-2.1.3.dist-info/METADATA
pycommando-2.1.3.dist-info/RECORD
