Metadata-Version: 2.1
Name: pycommando
Version: 2.1.3
Summary: A framework for batch processing.
Author: zztkm
Requires-Python: >=3.7,<4.0
Classifier: Programming Language :: Python :: 3
Classifier: Programming Language :: Python :: 3.10
Classifier: Programming Language :: Python :: 3.7
Classifier: Programming Language :: Python :: 3.8
Classifier: Programming Language :: Python :: 3.9
